influx_line.py
influx_line-1.0.0.dist-info/LICENSE
influx_line-1.0.0.dist-info/METADATA
influx_line-1.0.0.dist-info/WHEEL
influx_line-1.0.0.dist-info/top_level.txt
influx_line-1.0.0.dist-info/RECORD
