Metadata-Version: 2.1
Name: influx-line
Version: 1.0.0
Summary: Influx line protocol builder
Home-page: UNKNOWN
Author: Oluwatimilehin Akogun
Author-email: hello@timiakogun.com
License: UNKNOWN
Keywords: python,influx,influxdb,line protocol,flux,influx line protocol
Platform: UNKNOWN
Classifier: Intended Audience :: Developers
Classifier: Programming Language :: Python :: 3
Classifier: License :: OSI Approved :: MIT License
Classifier: Operating System :: OS Independent
Provides-Extra: dev
Requires-Dist: pytest >=3.7 ; extra == 'dev'
